fn/__init__.py
fn/either.py
fn/func.py
fn/iters.py
fn/monad.py
fn/op.py
fn/option.py
fn/recur.py
fn/stream.py
fn/underscore.py
fn/uniform.py
fn/immutable/__init__.py
fn/immutable/finger.py
fn/immutable/heap.py
fn/immutable/list.py
fn/immutable/trie.py
fn_mdowds-0.7.dist-info/METADATA
fn_mdowds-0.7.dist-info/RECORD
fn_mdowds-0.7.dist-info/WHEEL
fn_mdowds-0.7.dist-info/top_level.txt
