Metadata-Version: 2.1
Name: fn-mdowds
Version: 0.7
Summary: 
